setup.py
distributions_of_bernick/Binomialdistribution.py
distributions_of_bernick/Gaussiandistribution.py
distributions_of_bernick/Generaldistribution.py
distributions_of_bernick/__init__.py
distributions_of_bernick.egg-info/PKG-INFO
distributions_of_bernick.egg-info/SOURCES.txt
distributions_of_bernick.egg-info/dependency_links.txt
distributions_of_bernick.egg-info/not-zip-safe
distributions_of_bernick.egg-info/top_level.txt