Metadata-Version: 1.0
Name: distributions-of-bernick
Version: 0.1
Summary: Gaussian and Binomial distributions
Home-page: UNKNOWN
Author: Bernick Salvador
Author-email: UNKNOWN
License: UNKNOWN
Platform: UNKNOWN
